odoo/addons/product_category_name_translatable/README.rst
odoo/addons/product_category_name_translatable/__init__.py
odoo/addons/product_category_name_translatable/__manifest__.py
odoo/addons/product_category_name_translatable/i18n/it.po
odoo/addons/product_category_name_translatable/i18n/product_category_name_translatable.pot
odoo/addons/product_category_name_translatable/models/__init__.py
odoo/addons/product_category_name_translatable/models/product_category.py
odoo/addons/product_category_name_translatable/readme/CONTRIBUTORS.md
odoo/addons/product_category_name_translatable/readme/DESCRIPTION.md
odoo/addons/product_category_name_translatable/static/description/icon.png
odoo/addons/product_category_name_translatable/static/description/index.html
odoo/addons/product_category_name_translatable/tests/__init__.py
odoo/addons/product_category_name_translatable/tests/test_product_category_name_translatable.py
odoo_addon_product_category_name_translatable-18.0.1.0.0.4.dist-info/METADATA
odoo_addon_product_category_name_translatable-18.0.1.0.0.4.dist-info/WHEEL
odoo_addon_product_category_name_translatable-18.0.1.0.0.4.dist-info/top_level.txt
odoo_addon_product_category_name_translatable-18.0.1.0.0.4.dist-info/RECORD
